fpdf/__init__.py
fpdf/actions.py
fpdf/annotations.py
fpdf/bidi.py
fpdf/deprecation.py
fpdf/drawing.py
fpdf/encryption.py
fpdf/enums.py
fpdf/errors.py
fpdf/fonts.py
fpdf/fpdf.py
fpdf/graphics_state.py
fpdf/html.py
fpdf/image_datastructures.py
fpdf/image_parsing.py
fpdf/line_break.py
fpdf/linearization.py
fpdf/outline.py
fpdf/output.py
fpdf/prefs.py
fpdf/recorder.py
fpdf/sign.py
fpdf/structure_tree.py
fpdf/svg.py
fpdf/syntax.py
fpdf/table.py
fpdf/template.py
fpdf/text_region.py
fpdf/transitions.py
fpdf/util.py
fpdf2-2.7.8.dist-info/LICENSE
fpdf2-2.7.8.dist-info/METADATA
fpdf2-2.7.8.dist-info/WHEEL
fpdf2-2.7.8.dist-info/top_level.txt
fpdf2-2.7.8.dist-info/RECORD
