Metadata-Version: 2.1
Name: fpdf2
Version: 2.7.8
Summary: Simple & fast PDF generation for Python
Home-page: https://py-pdf.github.io/fpdf2/
Download-URL: https://github.com/py-pdf/fpdf2/tarball/2.7.8
Author: Olivier PLATHEY ported by Max
Maintainer: Lucas Cimon
License: LGPLv3+
Project-URL: Documentation, https://py-pdf.github.io/fpdf2/
Project-URL: Code, https://github.com/py-pdf/fpdf2
Project-URL: Issue tracker, https://github.com/py-pdf/fpdf2/issues
Keywords: pdf,unicode,png,jpg,ttf,barcode
Classifier: Development Status :: 5 - Production/Stable
Classifier: Intended Audience :: Developers
Classifier: License :: OSI Approved :: GNU Lesser General Public License v3 (LGPLv3)
Classifier: Programming Language :: Python
Classifier: Programming Language :: Python :: 3.7
Classifier: Programming Language :: Python :: 3.8
Classifier: Programming Language :: Python :: 3.9
Classifier: Programming Language :: Python :: 3.10
Classifier: Programming Language :: Python :: 3.11
Classifier: Programming Language :: Python :: 3.12
Classifier: Operating System :: OS Independent
Classifier: Topic :: Printing
Classifier: Topic :: Software Development :: Libraries :: Python Modules
Classifier: Topic :: Text Processing :: Markup
Classifier: Topic :: Multimedia :: Graphics
Classifier: Topic :: Multimedia :: Graphics :: Presentation
Requires-Python: >=3.7
License-File: LICENSE
Requires-Dist: defusedxml
Requires-Dist: Pillow!=9.2.*,>=6.2.2
Requires-Dist: fonttools>=4.34.0
